odoo/addons/purchase_stock_price_unit_sync/README.rst
odoo/addons/purchase_stock_price_unit_sync/__init__.py
odoo/addons/purchase_stock_price_unit_sync/__manifest__.py
odoo/addons/purchase_stock_price_unit_sync/i18n/purchase_stock_price_unit_sync.pot
odoo/addons/purchase_stock_price_unit_sync/models/__init__.py
odoo/addons/purchase_stock_price_unit_sync/models/purchase_order.py
odoo/addons/purchase_stock_price_unit_sync/readme/CONTRIBUTORS.rst
odoo/addons/purchase_stock_price_unit_sync/readme/DESCRIPTION.rst
odoo/addons/purchase_stock_price_unit_sync/static/description/icon.png
odoo/addons/purchase_stock_price_unit_sync/static/description/index.html
odoo/addons/purchase_stock_price_unit_sync/tests/__init__.py
odoo/addons/purchase_stock_price_unit_sync/tests/test_purchase_stock_price_unit_sync.py
odoo11_addon_purchase_stock_price_unit_sync-11.0.1.0.0.99.dev3.dist-info/METADATA
odoo11_addon_purchase_stock_price_unit_sync-11.0.1.0.0.99.dev3.dist-info/WHEEL
odoo11_addon_purchase_stock_price_unit_sync-11.0.1.0.0.99.dev3.dist-info/top_level.txt
odoo11_addon_purchase_stock_price_unit_sync-11.0.1.0.0.99.dev3.dist-info/RECORD
